register.v
/*
    Diego Bonilla, Enrique Macaya, Sebastian Lopez, Andres Antillon
    Project 1
    ECE 2372
    Dr. Juan Carlos Rojas
    Register module
*/

/*
    Register File Module
    Inputs:
        clk: Clock signal
        replaceData: Data to replace in the register
        replaceSel: Selector for the register to replace
        A_sel: Selector for register A
        B_sel: Selector for register B
    Outputs:
        A: Value passed to A
        B: Value passed to B
*/

module register_file(
    input clk, 
    input [7:0] replaceData, 
    input [3:0] replaceSel, 
    input [3:0] A_sel, 
    input [3:0] B_sel, 
    output [7:0] A, 
    output [7:0] B
);

    reg [7:0] regs[15:0];

    always @(posedge clk) begin
        regs[replaceSel] <= replaceData;
    end

    assign A = regs[A_sel];
    assign B = regs[B_sel];


endmodule

register_testbench.v
//Register Testbench 


`timescale 1ns / 1ns

module testbench();

//Inputs
    reg clk;
    reg [7:0] replaceData;
    reg [3:0] replaceSel, A_sel, B_sel;

//Outputs
    wire [7:0] A;
    wire [7:0] B;

    // Instantiate the Register File
    register_file uut (
        .clk(clk),
        .replaceData(replaceData),
        .replaceSel(replaceSel),
        .A_sel(A_sel),
        .B_sel(B_sel),
        .A(A),
        .B(B)
    );

    //Stimulus Waveform

   // Clock Generation
    initial begin
        clk = 0;
        forever #5 clk = ~clk; // Toggle `clk` every 5 time units
    end

    //Test stimulus
    initial begin
        // Write data into register 0
        replaceData = 8'hAA;
        replaceSel = 4'b0000;
        #10;

        // Select register 0 for output A and B
        A_sel = 4'b0000;
        B_sel = 4'b0000;
        #10;
        $display("A = %b, B = %b", A, B);

        // Write data into register 1
        replaceData = 8'hBB;
        replaceSel = 4'b0001;
        #10;

        // Select register 1 for output A and register 0 for output B
        A_sel = 4'b0001;
        B_sel = 4'b0000;
        #10; 
        $display("A = %b, B = %b", A, B);

        // Write data into register 2
        replaceData = 8'hCC;
        replaceSel = 4'b0010;
        #10;

        // Select register 2 for output A and register 1 for output B
        A_sel = 4'b0010;
        B_sel = 4'b0001;
        #10;
        $display("A = %b, B = %b", A, B);

        // Write data into register 3
        replaceData = 8'hDD;
        replaceSel = 4'b1111;
        #10;

        // Select register 3 for output A and register 1 for output B
        A_sel = 4'b1111;
        B_sel = 4'b0001;
        #10;
        $display("A = %b, B = %b", A, B);

        // Write data into register 4
        replaceData = 8'hEE;
        replaceSel = 4'b1010;
        #10;

        // Select register 4 for output A and register 1 for output B
        A_sel = 4'b1010;
        B_sel = 4'b1111;
        #10;
        $display("A = %b, B = %b", A, B);

        $finish;
    end

    initial begin
		$monitor("t=%3d clk=%b replaceSel=%b A_sel=%b B_sel=%b replaceData=%b A=%b B=%b", $time, clk, replaceSel, A_sel, B_sel, replaceData, A, B);
		$dumpfile("registertstb.vcd");
		$dumpvars(0, testbench);
	end

endmodule

registertstb.vcd
$date
	Mon Nov 04 23:11:27 2024
$end
$version
	Icarus Verilog
$end
$timescale
	1ns
$end
$scope module testbench $end
$var wire 8 ! B [7:0] $end
$var wire 8 " A [7:0] $end
$var reg 4 # A_sel [3:0] $end
$var reg 4 $ B_sel [3:0] $end
$var reg 1 % clk $end
$var reg 8 & replaceData [7:0] $end
$var reg 4 ' replaceSel [3:0] $end
$scope module uut $end
$var wire 8 ( A [7:0] $end
$var wire 4 ) A_sel [3:0] $end
$var wire 8 * B [7:0] $end
$var wire 4 + B_sel [3:0] $end
$var wire 1 % clk $end
$var wire 8 , replaceData [7:0] $end
$var wire 4 - replaceSel [3:0] $end
$upscope $end
$upscope $end
$enddefinitions $end
$comment Show the parameter values. $end
$dumpall
$end
#0
$dumpvars
b0 -
b10101010 ,
bx +
bx *
bx )
bx (
b0 '
b10101010 &
0%
bx $
bx #
bx "
bx !
$end
#5
1%
#10
0%
b10101010 !
b10101010 *
b0 $
b0 +
b10101010 "
b10101010 (
b0 #
b0 )
#15
1%
#20
0%
b1 '
b1 -
b10111011 &
b10111011 ,
#25
1%
#30
0%
b10111011 "
b10111011 (
b1 #
b1 )
#35
1%
#40
0%
b10 '
b10 -
b11001100 &
b11001100 ,
#45
1%
#50
0%
b10111011 !
b10111011 *
b1 $
b1 +
b11001100 "
b11001100 (
b10 #
b10 )
#55
1%
#60
0%
b1111 '
b1111 -
b11011101 &
b11011101 ,
#65
1%
#70
0%
b11011101 "
b11011101 (
b1111 #
b1111 )
#75
1%
#80
0%
b1010 '
b1010 -
b11101110 &
b11101110 ,
#85
1%
#90
0%
b11011101 !
b11011101 *
b1111 $
b1111 +
b11101110 "
b11101110 (
b1010 #
b1010 )
